diffusionLM/__init__.py
diffusionLM/model/MLP.py
diffusionLM/model/__init__.py
diffusionLM/model/attention.py
diffusionLM/model/diffusionLM.py
diffusionLM/model/mask_token.py
diffusionLM/model/time_embedding.py
diffusionLM/model/transformer_block.py
diffusionLM/model/transformers_model.py
diffusionLM/save_model/__init__.py
diffusionLM/save_model/model_save.py
diffusionLM/save_model/register_model.py
diffusionLM/trainer/__init__.py
diffusionLM/trainer/evaluate.py
diffusionLM/trainer/trainer.py
diffusionLM/utils/__init__.py
diffusionLM/utils/dataset.py
diffusionLM/utils/datasetANDtokenizer.py
diffusionLM/utils/error_handler.py
diffusionlm-0.1.9.dist-info/METADATA
diffusionlm-0.1.9.dist-info/WHEEL
diffusionlm-0.1.9.dist-info/top_level.txt
diffusionlm-0.1.9.dist-info/RECORD
