Metadata-Version: 2.4
Name: diffusionLM
Version: 0.1.9
Summary: A diffusion-based language model implementation
Author: Dark Coder
Author-email: codewithdark90@gmail.com
Project-URL: Homepage, https://github.com/codewithdark-git/DiffusionLM
Project-URL: Sponsor, https://github.com/sponsors/codewithdark-git
Classifier: Development Status :: 3 - Alpha
Classifier: Intended Audience :: Science/Research
Classifier: License :: OSI Approved :: MIT License
Classifier: Operating System :: OS Independent
Classifier: Programming Language :: Python :: 3.10
Classifier: Programming Language :: Python :: 3.11
Classifier: Programming Language :: Python :: 3.12
Classifier: Natural Language :: English
Classifier: Topic :: Scientific/Engineering :: Artificial Intelligence
Requires-Python: >=3.10
Requires-Dist: torch
Requires-Dist: transformers
Requires-Dist: datasets
Requires-Dist: numpy
Requires-Dist: tqdm
Requires-Dist: wandb
Requires-Dist: hydra-core
Requires-Dist: omegaconf
Requires-Dist: pytorch-lightning
Requires-Dist: accelerate
Dynamic: author
Dynamic: author-email
Dynamic: classifier
Dynamic: description
Dynamic: description-content-type
Dynamic: project-url
Dynamic: requires-dist
Dynamic: requires-python
Dynamic: summary
